threatrecognition/__init__.py
threatrecognition/main.py
threatrecognition-0.1.dist-info/METADATA
threatrecognition-0.1.dist-info/WHEEL
threatrecognition-0.1.dist-info/entry_points.txt
threatrecognition-0.1.dist-info/top_level.txt
threatrecognition-0.1.dist-info/RECORD
