Metadata-Version: 2.1
Name: threatrecognition
Version: 0.1
License: MIT
Requires-Dist: SpeechRecognition
Requires-Dist: pyaudio
